{"expireTime":9007200883554933000,"key":"8acbc9e3d136930a735be21f9e2c41be","val":{"name":"IMAGE_PROCESSING","inputPaths":["C:/Users/Hoon/blogGatsby/static/profile-image.png"],"outputDir":"C:/Users/Hoon/blogGatsby/public/static/f0275935346f4c86d3606837cfc4eab3","args":{"isLazy":false,"operations":[{"outputPath":"4a26a\\profile-image.png","args":{"height":30,"width":30,"cropFocus":17,"toFormat":"png","quality":100,"fit":"inside","background":"rgba(0,0,0,1)"}},{"outputPath":"1abf6\\profile-image.png","args":{"height":60,"width":60,"cropFocus":17,"toFormat":"png","quality":100,"fit":"inside","background":"rgba(0,0,0,1)"}},{"outputPath":"d9a67\\profile-image.png","args":{"height":120,"width":120,"cropFocus":17,"toFormat":"png","quality":100,"fit":"inside","background":"rgba(0,0,0,1)"}},{"outputPath":"5705b\\profile-image.png","args":{"height":180,"width":180,"cropFocus":17,"toFormat":"png","quality":100,"fit":"inside","background":"rgba(0,0,0,1)"}},{"outputPath":"e9b6f\\profile-image.png","args":{"height":240,"width":240,"cropFocus":17,"toFormat":"png","quality":100,"fit":"inside","background":"rgba(0,0,0,1)"}},{"outputPath":"bd357\\profile-image.png","args":{"height":650,"width":650,"cropFocus":17,"toFormat":"png","quality":100,"fit":"inside","background":"rgba(0,0,0,1)"}}],"pluginOptions":{"base64Width":20,"forceBase64Format":"","useMozJpeg":false,"stripMetadata":true,"lazyImageGeneration":true,"defaultQuality":50,"failOnError":true,"plugins":[]}}}}